{
	"chart": {
		"rootOrientation": "WEST",
		"container": "#tree-simple",
		"padding": 0,
		"connectors": {
			"type": "curve"
		},
		"node": {
			"HTMLclass": "nodeExample1"
		}
	},

	"nodeStructure":{
		"text":{"name":""},
		"children":[
			{
			"text":{"name":"in_port=3??1.0"},
			"children":[
				{"text":{"name":"R2,R18,R35,R37,R39,R41,R43,R45,R47"}, "HTMLclass":"rule_subset"}
			  ]
			 },
			{
			"text":{"name":"in_port=2??1.0"},
			"children":[
				{"text":{"name":"R0,R19,R21,R23,R25,R27,R29,R31,R33"}, "HTMLclass":"rule_subset"}
			  ]
			 },
			{
			"text":{"name":"in_port=9??1.0"},
			"children":[
				{"text":{"name":"R14,R30,R44,R56,R66,R74,R80,R84,R89"}, "HTMLclass":"rule_subset"}
			  ]
			 },
			{
			"text":{"name":"in_port=8??1.0"},
			"children":[
				{"text":{"name":"R12,R28,R42,R54,R64,R72,R78,R85,R87"}, "HTMLclass":"rule_subset"}
			  ]
			 },
			{
			"text":{"name":"in_port=6??1.0"},
			"children":[
				{"text":{"name":"R8,R24,R38,R50,R60,R71,R73,R75,R77"}, "HTMLclass":"rule_subset"}
			  ]
			 },
			{
			"text":{"name":"in_port=5??1.0"},
			"children":[
				{"text":{"name":"R6,R22,R36,R48,R61,R63,R65,R67,R69"}, "HTMLclass":"rule_subset"}
			  ]
			 },
			{
			"text":{"name":"in_port=1??1.0"},
			"children":[
				{"text":{"name":"R1,R3,R5,R7,R9,R11,R13,R15,R17"}, "HTMLclass":"rule_subset"}
			  ]
			 },
			{
			"text":{"name":"in_port=10??1.0"},
			"children":[
				{"text":{"name":"R16,R32,R46,R58,R68,R76,R82,R86,R88"}, "HTMLclass":"rule_subset"}
			  ]
			 },
			{
			"text":{"name":"in_port=7??1.0"},
			"children":[
				{"text":{"name":"R10,R26,R40,R52,R62,R70,R79,R81,R83"}, "HTMLclass":"rule_subset"}
			  ]
			 },
			{
			"text":{"name":"in_port=4??1.0"},
			"children":[
				{"text":{"name":"R4,R20,R34,R49,R51,R53,R55,R57,R59"}, "HTMLclass":"rule_subset"}
			  ]
			 }
			]
	}
}